{
  "id": "day:2017-10-2",
  "year": 2017,
  "month": 10,
  "day": 2,
  "entries": [
    {
      "id": "4892887d-c15b-410e-b1cf-4aa760c08c73",
      "description": "Est quibusdam occaecati est quos facilis.",
      "startTime": 1509617565365,
      "tags": [
        "client2"
      ],
      "finishTime": 1509618147689
    },
    {
      "id": "185c18c8-4e46-48e2-8d88-21f730776698",
      "description": "Suscipit quidem quaerat eum quia rerum cum.",
      "startTime": 1509617259158,
      "tags": [
        "Heaney - Gutkowski",
        "Kerluke and Sons",
        "tag2",
        "work"
      ],
      "finishTime": 1509617530825
    },
    {
      "id": "8beaaab3-5a9c-4f63-85dc-9d7b82336f2e",
      "description": "Consequatur ut natus sed.",
      "startTime": 1509615772574,
      "tags": [],
      "finishTime": 1509616815768
    },
    {
      "id": "57801b61-03bf-444b-8dad-739be63a0081",
      "description": "Sed quis unde quam architecto ratione quia et consectetur.",
      "startTime": 1509614875639,
      "tags": [
        "Heaney, Lockman and Klein",
        "Kerluke and Sons",
        "Tremblay and Sons"
      ],
      "finishTime": 1509615187405
    },
    {
      "id": "307d54c3-b474-491b-a2ae-7cc065ce74dd",
      "description": "Totam et facere ipsum fuga ut voluptatum voluptas exercitationem.",
      "startTime": 1509613662000,
      "tags": [
        "Kerluke and Sons",
        "Kiehn, Hermann and Kshlerin"
      ],
      "finishTime": 1509614602394
    },
    {
      "id": "956c458d-0602-492b-8407-4b6bcefa82be",
      "description": "Nisi voluptatem repellendus.",
      "startTime": 1509612498940,
      "tags": [],
      "finishTime": 1509613289555
    },
    {
      "id": "1d7d3764-05f7-4240-b33c-175aad5fab16",
      "description": "Quia nam voluptates ut eveniet nobis sint repellendus.",
      "startTime": 1509611877338,
      "tags": [
        "tag1",
        "Kerluke and Sons",
        "Heaney - Gutkowski",
        "work"
      ],
      "finishTime": 1509612243445
    },
    {
      "id": "81bbb5c4-3d2a-4261-beb7-e587c8eceeff",
      "description": "Nam aut ipsum tempore praesentium et quo eaque cumque.",
      "startTime": 1509610574372,
      "tags": [],
      "finishTime": 1509611560519
    },
    {
      "id": "0dc594b3-df02-4aef-8ddd-749847c4eb16",
      "description": "Quas iste in iure.",
      "startTime": 1509609792141,
      "tags": [
        "tag1",
        "client1",
        "tag2",
        "work"
      ],
      "finishTime": 1509610466044
    }
  ]
}