{
  "id": "day:2018-0-11",
  "year": 2018,
  "month": 0,
  "day": 11,
  "entries": [
    {
      "id": "5343e072-a805-4514-b162-c3b18a9b02f6",
      "description": "Non beatae porro accusamus ut debitis pariatur iusto.",
      "startTime": 1515667649618,
      "tags": [
        "Heaney, Lockman and Klein"
      ],
      "finishTime": 1515667970154
    },
    {
      "id": "457305e0-9f94-4ba3-955f-37b3307f10e5",
      "description": "Mollitia autem nisi blanditiis veritatis.",
      "startTime": 1515666513718,
      "tags": [
        "Keebler, Hermann and Hodkiewicz",
        "client1",
        "Heaney - Gutkowski"
      ],
      "finishTime": 1515667205719
    },
    {
      "id": "aa203cd0-07e2-4d25-819f-80486627fcd0",
      "description": "Id error ea occaecati in adipisci est.",
      "startTime": 1515665211631,
      "tags": [],
      "finishTime": 1515666184080
    },
    {
      "id": "b0331de8-6f16-47de-8a52-fc7f1e3785ee",
      "description": "Est quos assumenda dolorem.",
      "startTime": 1515664832901,
      "tags": [
        "work",
        "Heaney, Lockman and Klein",
        "Bahringer Group"
      ],
      "finishTime": 1515665057104
    },
    {
      "id": "a5371a48-dbd0-4c9f-a482-607e119014cf",
      "description": "Voluptatem iusto omnis quis.",
      "startTime": 1515663804891,
      "tags": [
        "client2",
        "Mertz, Block and Sauer",
        "Kiehn, Hermann and Kshlerin",
        "Heaney - Gutkowski"
      ],
      "finishTime": 1515664505507
    },
    {
      "id": "bf5712b9-920e-49bf-9a76-760a0e744378",
      "description": "Dolor ad totam quasi nam.",
      "startTime": 1515662943797,
      "tags": [
        "client1",
        "Heaney, Lockman and Klein",
        "tag1"
      ],
      "finishTime": 1515663340562
    },
    {
      "id": "2db19fb9-37f2-4caa-bb96-cbe31f6daedc",
      "description": "Suscipit exercitationem soluta quia.",
      "startTime": 1515662132573,
      "tags": [
        "work",
        "tag1"
      ],
      "finishTime": 1515662708643
    },
    {
      "id": "e11a1fd4-ac3a-45b0-9758-d6f96345892b",
      "description": "Maxime ea expedita blanditiis ipsam.",
      "startTime": 1515661167685,
      "tags": [],
      "finishTime": 1515661717096
    },
    {
      "id": "50d17d6b-b2cf-49fa-b06a-c71efccfcdb9",
      "description": "Nemo natus mollitia rerum rerum sequi.",
      "startTime": 1515660062328,
      "tags": [
        "Heaney - Gutkowski"
      ],
      "finishTime": 1515660952090
    },
    {
      "id": "8307d855-2a58-4725-8c1e-28161f6b8469",
      "description": "Quam iure dolor nihil et impedit quis velit.",
      "startTime": 1515659469959,
      "tags": [
        "client2"
      ],
      "finishTime": 1515659988175
    },
    {
      "id": "14b2c8d4-4f9b-4371-8cce-ebe0e3059657",
      "description": "Voluptatem est voluptatem.",
      "startTime": 1515658698509,
      "tags": [],
      "finishTime": 1515658905068
    },
    {
      "id": "69086453-67ff-417f-b701-16ed749081af",
      "description": "Non est ea ut minus optio aut quaerat.",
      "startTime": 1515657768298,
      "tags": [
        "tag3",
        "client1"
      ],
      "finishTime": 1515658388134
    }
  ]
}